tddbapi/__init__.py
tddbapi/conn.py
tddbapi/data.py
tddbapi/excp.py
tddbapi/util.py
tddbapi/interval/__init__.py
tddbapi/interval/months.py
tddbapi/interval/seconds.py
tddbapi-0.1.1.dist-info/METADATA
tddbapi-0.1.1.dist-info/WHEEL
tddbapi-0.1.1.dist-info/top_level.txt
tddbapi-0.1.1.dist-info/RECORD
