Metadata-Version: 2.1
Name: tddbapi
Version: 0.1.1
Summary: Pythonic shim over teradatasql, Teradata DB API driver
Home-page: https://bitbucket.org/padhia/tddbapi
License: UNKNOWN
Platform: UNKNOWN
Classifier: Development Status :: 3 - Alpha
Classifier: License :: OSI Approved :: MIT License
Classifier: Intended Audience :: Developers
Classifier: Topic :: Utilities
Classifier: Programming Language :: Python :: 3 :: Only
Classifier: Programming Language :: Python :: 3.8
Classifier: Programming Language :: Python :: 3.9
Requires-Python: >=3.8
Requires-Dist: teradatasql
